{"nodes":[{"id":"fwmrm.net","visited":0},{"id":"www.xboxygen.com","visited":1},{"id":"edition.cnn.com","visited":1},{"id":"www.01net.com","visited":1},{"id":"www.crunchyroll.com","visited":1},{"id":"www.letudiant.fr","visited":1}],"links":[{"source":"www.xboxygen.com","target":"fwmrm.net","cookie":6},{"source":"edition.cnn.com","target":"fwmrm.net","cookie":4},{"source":"www.01net.com","target":"fwmrm.net","cookie":1},{"source":"www.crunchyroll.com","target":"fwmrm.net","cookie":8},{"source":"www.letudiant.fr","target":"fwmrm.net","cookie":6}]}