{"nodes":[{"id":"imgur.com","visited":1,"icon":"icons/40.ico"},{"id":"www.baba-jana.com","visited":1},{"id":"www.babajana.com","visited":1},{"id":"moviesjoy.to","visited":1},{"id":"stackexchange.com","visited":1,"icon":"icons/117.ico"},{"id":"www.footlive.me","visited":1},{"id":"www.french-stream.lol","visited":1},{"id":"www.streamonsport.info","visited":1},{"id":"amazon-adsystem.com","visited":0},{"id":"doubleclick.net","visited":0,"icon":"icons/69.ico"},{"id":"facebook.com","visited":0,"icon":"icons/7.png"},{"id":"quantserve.com","visited":0}],"links":[{"source":"www.baba-jana.com","target":"imgur.com","cookie":7},{"source":"www.babajana.com","target":"imgur.com","cookie":7},{"source":"imgur.com","target":"amazon-adsystem.com","cookie":2},{"source":"imgur.com","target":"doubleclick.net","cookie":3},{"source":"imgur.com","target":"facebook.com","cookie":1},{"source":"imgur.com","target":"quantserve.com","cookie":3},{"source":"moviesjoy.to","target":"imgur.com","cookie":6},{"source":"stackexchange.com","target":"imgur.com","cookie":6},{"source":"www.footlive.me","target":"imgur.com","cookie":6},{"source":"www.french-stream.lol","target":"imgur.com","cookie":7},{"source":"www.streamonsport.info","target":"imgur.com","cookie":7}]}