{"nodes":[{"id":"sabavision.com","visited":0,"icon":"icons/78.gif"},{"id":"arga-mag.com","visited":1},{"id":"parsfootball.com","visited":1},{"id":"roozaneh.net","visited":1,"icon":"icons/71.ico"},{"id":"rooziato.com","visited":1},{"id":"www.aparat.com","visited":1},{"id":"www.asriran.com","visited":1},{"id":"www.chetor.com","visited":1},{"id":"www.eghtesadonline.com","visited":1},{"id":"www.gostaresh.news","visited":1},{"id":"www.rokna.net","visited":1},{"id":"www.tarafdari.com","visited":1}],"links":[{"source":"arga-mag.com","target":"sabavision.com","cookie":2},{"source":"parsfootball.com","target":"sabavision.com","cookie":3},{"source":"roozaneh.net","target":"sabavision.com","cookie":3},{"source":"rooziato.com","target":"sabavision.com","cookie":3},{"source":"www.aparat.com","target":"sabavision.com","cookie":3},{"source":"www.asriran.com","target":"sabavision.com","cookie":1},{"source":"www.chetor.com","target":"sabavision.com","cookie":3},{"source":"www.eghtesadonline.com","target":"sabavision.com","cookie":3},{"source":"www.gostaresh.news","target":"sabavision.com","cookie":3},{"source":"www.rokna.net","target":"sabavision.com","cookie":3},{"source":"www.tarafdari.com","target":"sabavision.com","cookie":4}]}