{"nodes":[{"id":"trafficjunky.net","visited":0},{"id":"e-hentai.org","visited":1,"icon":"icons/57.ico"},{"id":"fr.pornhub.com","visited":1},{"id":"fr.pornhubpremium.com","visited":1},{"id":"fr.stripchat.com","visited":1},{"id":"www.redtube.com","visited":1}],"links":[{"source":"e-hentai.org","target":"trafficjunky.net","cookie":3},{"source":"fr.pornhub.com","target":"trafficjunky.net","cookie":2},{"source":"fr.pornhubpremium.com","target":"trafficjunky.net","cookie":1},{"source":"fr.stripchat.com","target":"trafficjunky.net","cookie":1},{"source":"www.redtube.com","target":"trafficjunky.net","cookie":2}]}