{"nodes":[{"id":"www.viamichelin.fr","visited":1},{"id":"adnxs.com","visited":0},{"id":"demdex.net","visited":0},{"id":"mathtag.com","visited":0},{"id":"omtrdc.net","visited":0},{"id":"orangeads.fr","visited":0},{"id":"pubmatic.com","visited":0,"icon":"icons/206.ico"}],"links":[{"source":"www.viamichelin.fr","target":"adnxs.com","cookie":4},{"source":"www.viamichelin.fr","target":"demdex.net","cookie":3},{"source":"www.viamichelin.fr","target":"mathtag.com","cookie":3},{"source":"www.viamichelin.fr","target":"omtrdc.net","cookie":2},{"source":"www.viamichelin.fr","target":"orangeads.fr","cookie":2},{"source":"www.viamichelin.fr","target":"pubmatic.com","cookie":21}]}