{"nodes":[{"id":"www.francetvinfo.fr","visited":1},{"id":"doubleclick.net","visited":0,"icon":"icons/69.ico"},{"id":"facebook.com","visited":0,"icon":"icons/7.png"},{"id":"gigya.com","visited":0},{"id":"google.com","visited":0,"icon":"icons/0.ico"},{"id":"google.fr","visited":0,"icon":"icons/1.ico"},{"id":"xiti.com","visited":0,"icon":"icons/89.ico"}],"links":[{"source":"www.francetvinfo.fr","target":"doubleclick.net","cookie":2},{"source":"www.francetvinfo.fr","target":"facebook.com","cookie":1},{"source":"www.francetvinfo.fr","target":"gigya.com","cookie":7},{"source":"www.francetvinfo.fr","target":"google.com","cookie":2},{"source":"www.francetvinfo.fr","target":"google.fr","cookie":2},{"source":"www.francetvinfo.fr","target":"xiti.com","cookie":4}]}